[{"line":2,"elements":[{"start_timestamp":"2023-08-12T04:53:42.638Z","line":5,"name":"1.Validate you are able to create data in system","description":"","id":"valdiate-post-request-with-tags;1.validate-you-are-able-to-create-data-in-system","type":"scenario","keyword":"Scenario","steps":[{"result":{"duration":5570000000,"status":"passed"},"line":6,"name":"post the data to create user","match":{"location":"com.TagsValidationSD.TagsMessageValidation.post_the_data_to_create_user()"},"keyword":"Given "},{"result":{"duration":15000000,"status":"passed"},"line":7,"name":"validate status code is \"201\"","match":{"arguments":[{"val":"\"201\"","offset":24}],"location":"com.TagsValidationSD.TagsMessageValidation.validate_status_code_is(java.lang.String)"},"keyword":"Then "},{"result":{"duration":1953000000,"status":"passed"},"line":8,"name":"validate id created for user with non null value","match":{"location":"com.TagsValidationSD.TagsMessageValidation.validate_id_created_for_user_with_non_null_value()"},"keyword":"Then "},{"result":{"duration":78000000,"status":"passed"},"line":9,"name":"validate id created for user with non zero value","match":{"location":"com.TagsValidationSD.TagsMessageValidation.validate_id_created_for_user_with_non_zero_value()"},"keyword":"Then "}],"tags":[{"name":"@Regression"},{"name":"@smoke"},{"name":"@PostAPI"}]},{"start_timestamp":"2023-08-12T04:53:50.808Z","line":18,"name":"3.Validate you are able to create user from update File with name field","description":"","id":"valdiate-post-request-with-tags;3.validate-you-are-able-to-create-user-from-update-file-with-name-field","type":"scenario","keyword":"Scenario","steps":[{"result":{"error_message":"io.cucumber.core.exception.CucumberException: Step [post the data to create user from file with updated name] is defined with 1 parameters at 'com.TagsValidationSD.TagsMessageValidation.post_the_data_to_create_user_from_file_with_updated_name(io.cucumber.datatable.DataTable)'.\nHowever, the gherkin step has 0 arguments.\nStep text: post the data to create user from file with updated name\r\n\tat io.cucumber.core.runner.PickleStepDefinitionMatch.arityMismatch(PickleStepDefinitionMatch.java:83)\r\n\tat io.cucumber.core.runner.PickleStepDefinitionMatch.runStep(PickleStepDefinitionMatch.java:42)\r\n\tat io.cucumber.core.runner.ExecutionMode$1.execute(ExecutionMode.java:10)\r\n\tat io.cucumber.core.runner.TestStep.executeStep(TestStep.java:84)\r\n\tat io.cucumber.core.runner.TestStep.run(TestStep.java:56)\r\n\tat io.cucumber.core.runner.PickleStepTestStep.run(PickleStepTestStep.java:51)\r\n\tat io.cucumber.core.runner.TestCase.run(TestCase.java:84)\r\n\tat io.cucumber.core.runner.Runner.runPickle(Runner.java:75)\r\n\tat io.cucumber.junit.PickleRunners$NoStepDescriptions.lambda$run$0(PickleRunners.java:151)\r\n\tat io.cucumber.core.runtime.CucumberExecutionContext.lambda$runTestCase$5(CucumberExecutionContext.java:137)\r\n\tat io.cucumber.core.runtime.RethrowingThrowableCollector.executeAndThrow(RethrowingThrowableCollector.java:23)\r\n\tat io.cucumber.core.runtime.CucumberExecutionContext.runTestCase(CucumberExecutionContext.java:137)\r\n\tat io.cucumber.junit.PickleRunners$NoStepDescriptions.run(PickleRunners.java:148)\r\n\tat io.cucumber.junit.FeatureRunner.runChild(FeatureRunner.java:144)\r\n\tat io.cucumber.junit.FeatureRunner.runChild(FeatureRunner.java:28)\r\n\tat org.junit.runners.ParentRunner$4.run(ParentRunner.java:331)\r\n\tat org.junit.runners.ParentRunner$1.schedule(ParentRunner.java:79)\r\n\tat org.junit.runners.ParentRunner.runChildren(ParentRunner.java:329)\r\n\tat org.junit.runners.ParentRunner.access$100(ParentRunner.java:66)\r\n\tat org.junit.runners.ParentRunner$2.evaluate(ParentRunner.java:293)\r\n\tat org.junit.runners.ParentRunner$3.evaluate(ParentRunner.java:306)\r\n\tat org.junit.runners.ParentRunner.run(ParentRunner.java:413)\r\n\tat io.cucumber.junit.FeatureRunner.run(FeatureRunner.java:137)\r\n\tat io.cucumber.junit.Cucumber.runChild(Cucumber.java:196)\r\n\tat io.cucumber.junit.Cucumber.runChild(Cucumber.java:89)\r\n\tat org.junit.runners.ParentRunner$4.run(ParentRunner.java:331)\r\n\tat org.junit.runners.ParentRunner$1.schedule(ParentRunner.java:79)\r\n\tat org.junit.runners.ParentRunner.runChildren(ParentRunner.java:329)\r\n\tat org.junit.runners.ParentRunner.access$100(ParentRunner.java:66)\r\n\tat org.junit.runners.ParentRunner$2.evaluate(ParentRunner.java:293)\r\n\tat io.cucumber.core.runtime.CucumberExecutionContext.lambda$runFeatures$6(CucumberExecutionContext.java:148)\r\n\tat io.cucumber.core.runtime.CucumberExecutionContext.execute(CucumberExecutionContext.java:163)\r\n\tat io.cucumber.core.runtime.CucumberExecutionContext.runFeatures(CucumberExecutionContext.java:146)\r\n\tat io.cucumber.junit.Cucumber$StartAndFinishTestRun.evaluate(Cucumber.java:226)\r\n\tat org.junit.runners.ParentRunner$3.evaluate(ParentRunner.java:306)\r\n\tat org.junit.runners.ParentRunner.run(ParentRunner.java:413)\r\n\tat org.eclipse.jdt.internal.junit4.runner.JUnit4TestReference.run(JUnit4TestReference.java:93)\r\n\tat org.eclipse.jdt.internal.junit.runner.TestExecution.run(TestExecution.java:40)\r\n\tat org.eclipse.jdt.internal.junit.runner.RemoteTestRunner.runTests(RemoteTestRunner.java:529)\r\n\tat org.eclipse.jdt.internal.junit.runner.RemoteTestRunner.runTests(RemoteTestRunner.java:756)\r\n\tat org.eclipse.jdt.internal.junit.runner.RemoteTestRunner.run(RemoteTestRunner.java:452)\r\n\tat org.eclipse.jdt.internal.junit.runner.RemoteTestRunner.main(RemoteTestRunner.java:210)\r\n","duration":5000000,"status":"failed"},"line":19,"name":"post the data to create user from file with updated name","match":{"location":"com.TagsValidationSD.TagsMessageValidation.post_the_data_to_create_user_from_file_with_updated_name(io.cucumber.datatable.DataTable)"},"keyword":"Given "},{"result":{"status":"skipped"},"line":20,"name":"validate status code is \"201\"","match":{"arguments":[{"val":"\"201\"","offset":24}],"location":"com.TagsValidationSD.TagsMessageValidation.validate_status_code_is(java.lang.String)"},"keyword":"Then "},{"result":{"duration":1000000,"status":"skipped"},"line":21,"name":"validate id created for user with non null value","match":{"location":"com.TagsValidationSD.TagsMessageValidation.validate_id_created_for_user_with_non_null_value()"},"keyword":"Then "},{"result":{"duration":1000000,"status":"skipped"},"line":22,"name":"validate id created for user with non zero value","match":{"location":"com.TagsValidationSD.TagsMessageValidation.validate_id_created_for_user_with_non_zero_value()"},"keyword":"Then "}],"tags":[{"name":"@Regression"},{"name":"@smoke"}]}],"name":"valdiate POST request with tags","description":"","id":"valdiate-post-request-with-tags","keyword":"Feature","uri":"file:src/test/resources/com/TagsMessageValidationFF/ValidatePostRequest.feature","tags":[{"name":"@Regression","type":"Tag","location":{"line":1,"column":1}}]},{"line":2,"elements":[{"start_timestamp":"2023-08-12T04:53:50.879Z","line":43,"name":"6.Validate you are able to create user and delete the user","description":"","id":"valdiate-post-request-with-tags3;6.validate-you-are-able-to-create-user-and-delete-the-user","type":"scenario","keyword":"Scenario","steps":[{"result":{"duration":683000000,"status":"passed"},"line":44,"name":"post the data to create user from file with updated fields","match":{"location":"com.TagsValidationSD.TagsMessageValidation.post_the_data_to_create_user_from_file_with_updated_field(io.cucumber.datatable.DataTable)"},"rows":[{"cells":["name"]}],"keyword":"Given "},{"result":{"duration":1000000,"status":"passed"},"line":46,"name":"validate status code is \"201\"","match":{"arguments":[{"val":"\"201\"","offset":24}],"location":"com.TagsValidationSD.TagsMessageValidation.validate_status_code_is(java.lang.String)"},"keyword":"Then "},{"result":{"duration":65000000,"status":"passed"},"line":47,"name":"validate id created for user with non null value","match":{"location":"com.TagsValidationSD.TagsMessageValidation.validate_id_created_for_user_with_non_null_value()"},"keyword":"Then "},{"result":{"duration":74000000,"status":"passed"},"line":48,"name":"validate id created for user with non zero value","match":{"location":"com.TagsValidationSD.TagsMessageValidation.validate_id_created_for_user_with_non_zero_value()"},"keyword":"Then "},{"result":{"duration":574000000,"status":"passed"},"line":49,"name":"delete the user from system","match":{"location":"com.TagsValidationSD.TagsMessageValidation.delete_the_user_from_system()"},"keyword":"When "},{"result":{"duration":1000000,"status":"passed"},"line":50,"name":"validate user deleted from system","match":{"location":"com.TagsValidationSD.TagsMessageValidation.validate_user_deleted_from_system()"},"keyword":"Then "}],"tags":[{"name":"@Regression"},{"name":"@smoke"}]}],"name":"valdiate POST request with tags3","description":"","id":"valdiate-post-request-with-tags3","keyword":"Feature","uri":"file:src/test/resources/com/TagsMessageValidationFF/ValidatePostRequest3.feature","tags":[{"name":"@Regression","type":"Tag","location":{"line":1,"column":1}}]}]